<?xml version="1.0" encoding="UTF-8" standalone="yes"?><p:sld xmlns:a="http://schemas.openxmlformats.org/drawingml/2006/main" xmlns:r="http://schemas.openxmlformats.org/officeDocument/2006/relationships" xmlns:mc="http://schemas.openxmlformats.org/markup-compatibility/2006" xmlns:mv="urn:schemas-microsoft-com:mac:vml" xmlns:p="http://schemas.openxmlformats.org/presentationml/2006/main" xmlns:c="http://schemas.openxmlformats.org/drawingml/2006/chart" xmlns:dgm="http://schemas.openxmlformats.org/drawingml/2006/diagram" xmlns:o="urn:schemas-microsoft-com:office:office" xmlns:v="urn:schemas-microsoft-com:vml" xmlns:pvml="urn:schemas-microsoft-com:office:powerpoint" xmlns:com="http://schemas.openxmlformats.org/drawingml/2006/compatibility" xmlns:p14="http://schemas.microsoft.com/office/powerpoint/2010/main" xmlns:p15="http://schemas.microsoft.com/office/powerpoint/2012/main" xmlns:ahyp="http://schemas.microsoft.com/office/drawing/2018/hyperlinkcolor"><p:cSld><p:spTree><p:nvGrpSpPr><p:cNvPr id="464" name="Shape 464"/><p:cNvGrpSpPr/><p:nvPr/></p:nvGrpSpPr><p:grpSpPr><a:xfrm><a:off x="0" y="0"/><a:ext cx="0" cy="0"/><a:chOff x="0" y="0"/><a:chExt cx="0" cy="0"/></a:xfrm></p:grpSpPr><p:sp><p:nvSpPr><p:cNvPr id="465" name="Google Shape;465;p11"/><p:cNvSpPr txBox="1"/><p:nvPr/></p:nvSpPr><p:spPr><a:xfrm><a:off x="533400" y="568325"/><a:ext cx="1532792" cy="307777"/></a:xfrm><a:prstGeom prst="rect"><a:avLst/></a:prstGeom><a:noFill/><a:ln><a:noFill/></a:ln></p:spPr><p:txBody><a:bodyPr anchorCtr="0" anchor="t" bIns="45700" lIns="91425" spcFirstLastPara="1" rIns="91425" wrap="square" tIns="45700"><a:spAutoFit/></a:bodyPr><a:lstStyle/><a:p><a:pPr indent="0" lvl="0" marL="0" marR="0" rtl="0" algn="l"><a:lnSpc><a:spcPct val="100000"/></a:lnSpc><a:spcBef><a:spcPts val="0"/></a:spcBef><a:spcAft><a:spcPts val="0"/></a:spcAft><a:buClr><a:srgbClr val="000000"/></a:buClr><a:buSzPts val="1400"/><a:buFont typeface="Arial"/><a:buNone/></a:pPr><a:r><a:rPr b="0" i="0" lang="en-US" sz="1400" u="none" cap="none" strike="noStrike"><a:solidFill><a:schemeClr val="dk1"/></a:solidFill><a:latin typeface="Poppins"/><a:ea typeface="Poppins"/><a:cs typeface="Poppins"/><a:sym typeface="Poppins"/></a:rPr><a:t>Your Company</a:t></a:r><a:endParaRPr b="0" i="0" sz="1400" u="none" cap="none" strike="noStrike"><a:solidFill><a:srgbClr val="000000"/></a:solidFill><a:latin typeface="Arial"/><a:ea typeface="Arial"/><a:cs typeface="Arial"/><a:sym typeface="Arial"/></a:endParaRPr></a:p></p:txBody></p:sp><p:sp><p:nvSpPr><p:cNvPr id="466" name="Google Shape;466;p11"/><p:cNvSpPr/><p:nvPr/></p:nvSpPr><p:spPr><a:xfrm><a:off x="6797674" y="527050"/><a:ext cx="3409037" cy="342900"/></a:xfrm><a:prstGeom prst="roundRect"><a:avLst><a:gd fmla="val 50000" name="adj"/></a:avLst></a:prstGeom><a:solidFill><a:schemeClr val="lt2"/></a:solidFill><a:ln cap="flat" cmpd="sng" w="12700"><a:solidFill><a:schemeClr val="accent2"/></a:solidFill><a:prstDash val="solid"/><a:miter lim="800000"/><a:headEnd len="sm" w="sm" type="none"/><a:tailEnd len="sm" w="sm" type="none"/></a:ln><a:effectLst><a:outerShdw blurRad="50800" rotWithShape="0" algn="tl" dir="2700000" dist="38100"><a:srgbClr val="000000"><a:alpha val="40000"/></a:srgbClr></a:outerShdw></a:effectLst></p:spPr><p:txBody><a:bodyPr anchorCtr="0" anchor="ctr" bIns="45700" lIns="91425" spcFirstLastPara="1" rIns="91425" wrap="square" tIns="45700"><a:noAutofit/></a:bodyPr><a:lstStyle/><a:p><a:pPr indent="0" lvl="0" marL="0" marR="0" rtl="0" algn="ctr"><a:lnSpc><a:spcPct val="100000"/></a:lnSpc><a:spcBef><a:spcPts val="0"/></a:spcBef><a:spcAft><a:spcPts val="0"/></a:spcAft><a:buClr><a:srgbClr val="000000"/></a:buClr><a:buSzPts val="1800"/><a:buFont typeface="Arial"/><a:buNone/></a:pPr><a:r><a:t></a:t></a:r><a:endParaRPr b="0" i="0" sz="1800" u="none" cap="none" strike="noStrike"><a:solidFill><a:schemeClr val="lt1"/></a:solidFill><a:latin typeface="Poppins"/><a:ea typeface="Poppins"/><a:cs typeface="Poppins"/><a:sym typeface="Poppins"/></a:endParaRPr></a:p></p:txBody></p:sp><p:sp><p:nvSpPr><p:cNvPr id="467" name="Google Shape;467;p11"/><p:cNvSpPr/><p:nvPr/></p:nvSpPr><p:spPr><a:xfrm><a:off x="10560050" y="527050"/><a:ext cx="1098549" cy="342900"/></a:xfrm><a:prstGeom prst="roundRect"><a:avLst><a:gd fmla="val 50000" name="adj"/></a:avLst></a:prstGeom><a:solidFill><a:schemeClr val="accent2"/></a:solidFill><a:ln cap="flat" cmpd="sng" w="12700"><a:solidFill><a:schemeClr val="accent1"/></a:solidFill><a:prstDash val="solid"/><a:miter lim="800000"/><a:headEnd len="sm" w="sm" type="none"/><a:tailEnd len="sm" w="sm" type="none"/></a:ln><a:effectLst><a:outerShdw blurRad="50800" rotWithShape="0" algn="tl" dir="2700000" dist="38100"><a:srgbClr val="000000"><a:alpha val="40000"/></a:srgbClr></a:outerShdw></a:effectLst></p:spPr><p:txBody><a:bodyPr anchorCtr="0" anchor="ctr" bIns="45700" lIns="91425" spcFirstLastPara="1" rIns="91425" wrap="square" tIns="45700"><a:noAutofit/></a:bodyPr><a:lstStyle/><a:p><a:pPr indent="0" lvl="0" marL="0" marR="0" rtl="0" algn="ctr"><a:lnSpc><a:spcPct val="100000"/></a:lnSpc><a:spcBef><a:spcPts val="0"/></a:spcBef><a:spcAft><a:spcPts val="0"/></a:spcAft><a:buClr><a:srgbClr val="000000"/></a:buClr><a:buSzPts val="1800"/><a:buFont typeface="Arial"/><a:buNone/></a:pPr><a:r><a:t></a:t></a:r><a:endParaRPr b="0" i="0" sz="1800" u="none" cap="none" strike="noStrike"><a:solidFill><a:schemeClr val="lt1"/></a:solidFill><a:latin typeface="Poppins"/><a:ea typeface="Poppins"/><a:cs typeface="Poppins"/><a:sym typeface="Poppins"/></a:endParaRPr></a:p></p:txBody></p:sp><p:sp><p:nvSpPr><p:cNvPr id="468" name="Google Shape;468;p11"/><p:cNvSpPr txBox="1"/><p:nvPr/></p:nvSpPr><p:spPr><a:xfrm><a:off x="10784556" y="577850"/><a:ext cx="678391" cy="261610"/></a:xfrm><a:prstGeom prst="rect"><a:avLst/></a:prstGeom><a:noFill/><a:ln><a:noFill/></a:ln></p:spPr><p:txBody><a:bodyPr anchorCtr="0" anchor="t" bIns="45700" lIns="91425" spcFirstLastPara="1" rIns="91425" wrap="square" tIns="45700"><a:spAutoFit/></a:bodyPr><a:lstStyle/><a:p><a:pPr indent="0" lvl="0" marL="0" marR="0" rtl="0" algn="r"><a:lnSpc><a:spcPct val="100000"/></a:lnSpc><a:spcBef><a:spcPts val="0"/></a:spcBef><a:spcAft><a:spcPts val="0"/></a:spcAft><a:buClr><a:srgbClr val="000000"/></a:buClr><a:buSzPts val="1100"/><a:buFont typeface="Arial"/><a:buNone/></a:pPr><a:r><a:rPr b="0" i="0" lang="en-US" sz="1100" u="none" cap="none" strike="noStrike"><a:solidFill><a:schemeClr val="lt1"/></a:solidFill><a:latin typeface="Poppins"/><a:ea typeface="Poppins"/><a:cs typeface="Poppins"/><a:sym typeface="Poppins"/></a:rPr><a:t>Search</a:t></a:r><a:endParaRPr b="0" i="0" sz="1400" u="none" cap="none" strike="noStrike"><a:solidFill><a:srgbClr val="000000"/></a:solidFill><a:latin typeface="Arial"/><a:ea typeface="Arial"/><a:cs typeface="Arial"/><a:sym typeface="Arial"/></a:endParaRPr></a:p></p:txBody></p:sp><p:sp><p:nvSpPr><p:cNvPr id="469" name="Google Shape;469;p11"/><p:cNvSpPr txBox="1"/><p:nvPr/></p:nvSpPr><p:spPr><a:xfrm><a:off x="7133321" y="577850"/><a:ext cx="606256" cy="261610"/></a:xfrm><a:prstGeom prst="rect"><a:avLst/></a:prstGeom><a:noFill/><a:ln><a:noFill/></a:ln></p:spPr><p:txBody><a:bodyPr anchorCtr="0" anchor="t" bIns="45700" lIns="91425" spcFirstLastPara="1" rIns="91425" wrap="square" tIns="45700"><a:spAutoFit/></a:bodyPr><a:lstStyle/><a:p><a:pPr indent="0" lvl="0" marL="0" marR="0" rtl="0" algn="l"><a:lnSpc><a:spcPct val="100000"/></a:lnSpc><a:spcBef><a:spcPts val="0"/></a:spcBef><a:spcAft><a:spcPts val="0"/></a:spcAft><a:buClr><a:srgbClr val="000000"/></a:buClr><a:buSzPts val="1100"/><a:buFont typeface="Arial"/><a:buNone/></a:pPr><a:r><a:rPr b="0" i="0" lang="en-US" sz="1100" u="none" cap="none" strike="noStrike"><a:solidFill><a:schemeClr val="dk1"/></a:solidFill><a:latin typeface="Poppins"/><a:ea typeface="Poppins"/><a:cs typeface="Poppins"/><a:sym typeface="Poppins"/></a:rPr><a:t>Home</a:t></a:r><a:endParaRPr b="0" i="0" sz="1400" u="none" cap="none" strike="noStrike"><a:solidFill><a:srgbClr val="000000"/></a:solidFill><a:latin typeface="Arial"/><a:ea typeface="Arial"/><a:cs typeface="Arial"/><a:sym typeface="Arial"/></a:endParaRPr></a:p></p:txBody></p:sp><p:sp><p:nvSpPr><p:cNvPr id="470" name="Google Shape;470;p11"/><p:cNvSpPr txBox="1"/><p:nvPr/></p:nvSpPr><p:spPr><a:xfrm><a:off x="8099690" y="577850"/><a:ext cx="809837" cy="261610"/></a:xfrm><a:prstGeom prst="rect"><a:avLst/></a:prstGeom><a:noFill/><a:ln><a:noFill/></a:ln></p:spPr><p:txBody><a:bodyPr anchorCtr="0" anchor="t" bIns="45700" lIns="91425" spcFirstLastPara="1" rIns="91425" wrap="square" tIns="45700"><a:spAutoFit/></a:bodyPr><a:lstStyle/><a:p><a:pPr indent="0" lvl="0" marL="0" marR="0" rtl="0" algn="ctr"><a:lnSpc><a:spcPct val="100000"/></a:lnSpc><a:spcBef><a:spcPts val="0"/></a:spcBef><a:spcAft><a:spcPts val="0"/></a:spcAft><a:buClr><a:srgbClr val="000000"/></a:buClr><a:buSzPts val="1100"/><a:buFont typeface="Arial"/><a:buNone/></a:pPr><a:r><a:rPr b="0" i="0" lang="en-US" sz="1100" u="none" cap="none" strike="noStrike"><a:solidFill><a:schemeClr val="dk1"/></a:solidFill><a:latin typeface="Poppins"/><a:ea typeface="Poppins"/><a:cs typeface="Poppins"/><a:sym typeface="Poppins"/></a:rPr><a:t>About Us</a:t></a:r><a:endParaRPr b="0" i="0" sz="1400" u="none" cap="none" strike="noStrike"><a:solidFill><a:srgbClr val="000000"/></a:solidFill><a:latin typeface="Arial"/><a:ea typeface="Arial"/><a:cs typeface="Arial"/><a:sym typeface="Arial"/></a:endParaRPr></a:p></p:txBody></p:sp><p:sp><p:nvSpPr><p:cNvPr id="471" name="Google Shape;471;p11"/><p:cNvSpPr txBox="1"/><p:nvPr/></p:nvSpPr><p:spPr><a:xfrm><a:off x="9277655" y="577850"/><a:ext cx="755335" cy="261610"/></a:xfrm><a:prstGeom prst="rect"><a:avLst/></a:prstGeom><a:noFill/><a:ln><a:noFill/></a:ln></p:spPr><p:txBody><a:bodyPr anchorCtr="0" anchor="t" bIns="45700" lIns="91425" spcFirstLastPara="1" rIns="91425" wrap="square" tIns="45700"><a:spAutoFit/></a:bodyPr><a:lstStyle/><a:p><a:pPr indent="0" lvl="0" marL="0" marR="0" rtl="0" algn="r"><a:lnSpc><a:spcPct val="100000"/></a:lnSpc><a:spcBef><a:spcPts val="0"/></a:spcBef><a:spcAft><a:spcPts val="0"/></a:spcAft><a:buClr><a:srgbClr val="000000"/></a:buClr><a:buSzPts val="1100"/><a:buFont typeface="Arial"/><a:buNone/></a:pPr><a:r><a:rPr b="0" i="0" lang="en-US" sz="1100" u="none" cap="none" strike="noStrike"><a:solidFill><a:schemeClr val="dk1"/></a:solidFill><a:latin typeface="Poppins"/><a:ea typeface="Poppins"/><a:cs typeface="Poppins"/><a:sym typeface="Poppins"/></a:rPr><a:t>Contact</a:t></a:r><a:endParaRPr b="0" i="0" sz="1400" u="none" cap="none" strike="noStrike"><a:solidFill><a:srgbClr val="000000"/></a:solidFill><a:latin typeface="Arial"/><a:ea typeface="Arial"/><a:cs typeface="Arial"/><a:sym typeface="Arial"/></a:endParaRPr></a:p></p:txBody></p:sp><p:grpSp><p:nvGrpSpPr><p:cNvPr id="472" name="Google Shape;472;p11"/><p:cNvGrpSpPr/><p:nvPr/></p:nvGrpSpPr><p:grpSpPr><a:xfrm><a:off x="6997702" y="669152"/><a:ext cx="95248" cy="68286"/><a:chOff x="3790" y="2022"/><a:chExt cx="282" cy="150"/></a:xfrm></p:grpSpPr><p:cxnSp><p:nvCxnSpPr><p:cNvPr id="473" name="Google Shape;473;p11"/><p:cNvCxnSpPr/><p:nvPr/></p:nvCxnSpPr><p:spPr><a:xfrm><a:off x="3790" y="2172"/><a:ext cx="282" cy="0"/></a:xfrm><a:prstGeom prst="straightConnector1"><a:avLst/></a:prstGeom><a:noFill/><a:ln cap="flat" cmpd="sng" w="12700"><a:solidFill><a:srgbClr val="000000"/></a:solidFill><a:prstDash val="solid"/><a:miter lim="800000"/><a:headEnd len="sm" w="sm" type="none"/><a:tailEnd len="sm" w="sm" type="none"/></a:ln></p:spPr></p:cxnSp><p:cxnSp><p:nvCxnSpPr><p:cNvPr id="474" name="Google Shape;474;p11"/><p:cNvCxnSpPr/><p:nvPr/></p:nvCxnSpPr><p:spPr><a:xfrm><a:off x="3790" y="2097"/><a:ext cx="282" cy="0"/></a:xfrm><a:prstGeom prst="straightConnector1"><a:avLst/></a:prstGeom><a:noFill/><a:ln cap="flat" cmpd="sng" w="12700"><a:solidFill><a:srgbClr val="000000"/></a:solidFill><a:prstDash val="solid"/><a:miter lim="800000"/><a:headEnd len="sm" w="sm" type="none"/><a:tailEnd len="sm" w="sm" type="none"/></a:ln></p:spPr></p:cxnSp><p:cxnSp><p:nvCxnSpPr><p:cNvPr id="475" name="Google Shape;475;p11"/><p:cNvCxnSpPr/><p:nvPr/></p:nvCxnSpPr><p:spPr><a:xfrm><a:off x="3790" y="2022"/><a:ext cx="282" cy="0"/></a:xfrm><a:prstGeom prst="straightConnector1"><a:avLst/></a:prstGeom><a:noFill/><a:ln cap="flat" cmpd="sng" w="12700"><a:solidFill><a:srgbClr val="000000"/></a:solidFill><a:prstDash val="solid"/><a:miter lim="800000"/><a:headEnd len="sm" w="sm" type="none"/><a:tailEnd len="sm" w="sm" type="none"/></a:ln></p:spPr></p:cxnSp></p:grpSp><p:sp><p:nvSpPr><p:cNvPr id="476" name="Google Shape;476;p11"/><p:cNvSpPr txBox="1"/><p:nvPr/></p:nvSpPr><p:spPr><a:xfrm><a:off x="6745399" y="1414848"/><a:ext cx="5064512" cy="1446550"/></a:xfrm><a:prstGeom prst="rect"><a:avLst/></a:prstGeom><a:noFill/><a:ln><a:noFill/></a:ln></p:spPr><p:txBody><a:bodyPr anchorCtr="0" anchor="t" bIns="45700" lIns="91425" spcFirstLastPara="1" rIns="91425" wrap="square" tIns="45700"><a:spAutoFit/></a:bodyPr><a:lstStyle/><a:p><a:pPr indent="0" lvl="0" marL="0" marR="0" rtl="0" algn="l"><a:lnSpc><a:spcPct val="100000"/></a:lnSpc><a:spcBef><a:spcPts val="0"/></a:spcBef><a:spcAft><a:spcPts val="0"/></a:spcAft><a:buClr><a:srgbClr val="000000"/></a:buClr><a:buSzPts val="4400"/><a:buFont typeface="Arial"/><a:buNone/></a:pPr><a:r><a:rPr b="0" i="0" lang="en-US" sz="4400" u="none" cap="none" strike="noStrike"><a:solidFill><a:schemeClr val="dk1"/></a:solidFill><a:latin typeface="Poppins Medium"/><a:ea typeface="Poppins Medium"/><a:cs typeface="Poppins Medium"/><a:sym typeface="Poppins Medium"/></a:rPr><a:t>Our Key Advantages.</a:t></a:r><a:endParaRPr b="0" i="0" sz="1400" u="none" cap="none" strike="noStrike"><a:solidFill><a:srgbClr val="000000"/></a:solidFill><a:latin typeface="Arial"/><a:ea typeface="Arial"/><a:cs typeface="Arial"/><a:sym typeface="Arial"/></a:endParaRPr></a:p></p:txBody></p:sp><p:sp><p:nvSpPr><p:cNvPr id="477" name="Google Shape;477;p11"/><p:cNvSpPr txBox="1"/><p:nvPr/></p:nvSpPr><p:spPr><a:xfrm><a:off x="952501" y="1475760"/><a:ext cx="3736045" cy="400110"/></a:xfrm><a:prstGeom prst="rect"><a:avLst/></a:prstGeom><a:noFill/><a:ln><a:noFill/></a:ln></p:spPr><p:txBody><a:bodyPr anchorCtr="0" anchor="t" bIns="45700" lIns="91425" spcFirstLastPara="1" rIns="91425" wrap="square" tIns="45700"><a:spAutoFit/></a:bodyPr><a:lstStyle/><a:p><a:pPr indent="0" lvl="0" marL="0" marR="0" rtl="0" algn="l"><a:lnSpc><a:spcPct val="100000"/></a:lnSpc><a:spcBef><a:spcPts val="0"/></a:spcBef><a:spcAft><a:spcPts val="0"/></a:spcAft><a:buClr><a:srgbClr val="000000"/></a:buClr><a:buSzPts val="2000"/><a:buFont typeface="Arial"/><a:buNone/></a:pPr><a:r><a:rPr b="0" i="0" lang="en-US" sz="2000" u="none" cap="none" strike="noStrike"><a:solidFill><a:schemeClr val="dk1"/></a:solidFill><a:latin typeface="Poppins"/><a:ea typeface="Poppins"/><a:cs typeface="Poppins"/><a:sym typeface="Poppins"/></a:rPr><a:t>Cutting-Edge Technology</a:t></a:r><a:endParaRPr b="0" i="0" sz="1400" u="none" cap="none" strike="noStrike"><a:solidFill><a:srgbClr val="000000"/></a:solidFill><a:latin typeface="Arial"/><a:ea typeface="Arial"/><a:cs typeface="Arial"/><a:sym typeface="Arial"/></a:endParaRPr></a:p></p:txBody></p:sp><p:sp><p:nvSpPr><p:cNvPr id="478" name="Google Shape;478;p11"/><p:cNvSpPr txBox="1"/><p:nvPr/></p:nvSpPr><p:spPr><a:xfrm><a:off x="952500" y="1917611"/><a:ext cx="3096204" cy="620170"/></a:xfrm><a:prstGeom prst="rect"><a:avLst/></a:prstGeom><a:noFill/><a:ln><a:noFill/></a:ln></p:spPr><p:txBody><a:bodyPr anchorCtr="0" anchor="t" bIns="45700" lIns="91425" spcFirstLastPara="1" rIns="91425" wrap="square" tIns="45700"><a:spAutoFit/></a:bodyPr><a:lstStyle/><a:p><a:pPr indent="0" lvl="0" marL="0" marR="0" rtl="0" algn="l"><a:lnSpc><a:spcPct val="150000"/></a:lnSpc><a:spcBef><a:spcPts val="0"/></a:spcBef><a:spcAft><a:spcPts val="0"/></a:spcAft><a:buClr><a:srgbClr val="000000"/></a:buClr><a:buSzPts val="1200"/><a:buFont typeface="Arial"/><a:buNone/></a:pPr><a:r><a:rPr b="0" i="0" lang="en-US" sz="1200" u="none" cap="none" strike="noStrike"><a:solidFill><a:schemeClr val="dk1"/></a:solidFill><a:latin typeface="Poppins"/><a:ea typeface="Poppins"/><a:cs typeface="Poppins"/><a:sym typeface="Poppins"/></a:rPr><a:t>Even the all-powerful Pointing has no control about the blind texts.</a:t></a:r><a:endParaRPr b="1" i="0" sz="1200" u="none" cap="none" strike="noStrike"><a:solidFill><a:schemeClr val="dk1"/></a:solidFill><a:latin typeface="Poppins"/><a:ea typeface="Poppins"/><a:cs typeface="Poppins"/><a:sym typeface="Poppins"/></a:endParaRPr></a:p></p:txBody></p:sp><p:cxnSp><p:nvCxnSpPr><p:cNvPr id="479" name="Google Shape;479;p11"/><p:cNvCxnSpPr/><p:nvPr/></p:nvCxnSpPr><p:spPr><a:xfrm><a:off x="1066855" y="2727087"/><a:ext cx="3736046" cy="0"/></a:xfrm><a:prstGeom prst="straightConnector1"><a:avLst/></a:prstGeom><a:noFill/><a:ln cap="flat" cmpd="sng" w="19050"><a:solidFill><a:schemeClr val="accent3"/></a:solidFill><a:prstDash val="solid"/><a:miter lim="800000"/><a:headEnd len="sm" w="sm" type="none"/><a:tailEnd len="sm" w="sm" type="none"/></a:ln></p:spPr></p:cxnSp><p:sp><p:nvSpPr><p:cNvPr id="480" name="Google Shape;480;p11"/><p:cNvSpPr txBox="1"/><p:nvPr/></p:nvSpPr><p:spPr><a:xfrm><a:off x="952502" y="3053733"/><a:ext cx="2854902" cy="400110"/></a:xfrm><a:prstGeom prst="rect"><a:avLst/></a:prstGeom><a:noFill/><a:ln><a:noFill/></a:ln></p:spPr><p:txBody><a:bodyPr anchorCtr="0" anchor="t" bIns="45700" lIns="91425" spcFirstLastPara="1" rIns="91425" wrap="square" tIns="45700"><a:spAutoFit/></a:bodyPr><a:lstStyle/><a:p><a:pPr indent="0" lvl="0" marL="0" marR="0" rtl="0" algn="l"><a:lnSpc><a:spcPct val="100000"/></a:lnSpc><a:spcBef><a:spcPts val="0"/></a:spcBef><a:spcAft><a:spcPts val="0"/></a:spcAft><a:buClr><a:srgbClr val="000000"/></a:buClr><a:buSzPts val="2000"/><a:buFont typeface="Arial"/><a:buNone/></a:pPr><a:r><a:rPr b="0" i="0" lang="en-US" sz="2000" u="none" cap="none" strike="noStrike"><a:solidFill><a:schemeClr val="dk1"/></a:solidFill><a:latin typeface="Poppins"/><a:ea typeface="Poppins"/><a:cs typeface="Poppins"/><a:sym typeface="Poppins"/></a:rPr><a:t>Tailored Solutions</a:t></a:r><a:endParaRPr b="0" i="0" sz="1400" u="none" cap="none" strike="noStrike"><a:solidFill><a:srgbClr val="000000"/></a:solidFill><a:latin typeface="Arial"/><a:ea typeface="Arial"/><a:cs typeface="Arial"/><a:sym typeface="Arial"/></a:endParaRPr></a:p></p:txBody></p:sp><p:sp><p:nvSpPr><p:cNvPr id="481" name="Google Shape;481;p11"/><p:cNvSpPr txBox="1"/><p:nvPr/></p:nvSpPr><p:spPr><a:xfrm><a:off x="952500" y="3495584"/><a:ext cx="3096204" cy="620170"/></a:xfrm><a:prstGeom prst="rect"><a:avLst/></a:prstGeom><a:noFill/><a:ln><a:noFill/></a:ln></p:spPr><p:txBody><a:bodyPr anchorCtr="0" anchor="t" bIns="45700" lIns="91425" spcFirstLastPara="1" rIns="91425" wrap="square" tIns="45700"><a:spAutoFit/></a:bodyPr><a:lstStyle/><a:p><a:pPr indent="0" lvl="0" marL="0" marR="0" rtl="0" algn="l"><a:lnSpc><a:spcPct val="150000"/></a:lnSpc><a:spcBef><a:spcPts val="0"/></a:spcBef><a:spcAft><a:spcPts val="0"/></a:spcAft><a:buClr><a:srgbClr val="000000"/></a:buClr><a:buSzPts val="1200"/><a:buFont typeface="Arial"/><a:buNone/></a:pPr><a:r><a:rPr b="0" i="0" lang="en-US" sz="1200" u="none" cap="none" strike="noStrike"><a:solidFill><a:schemeClr val="dk1"/></a:solidFill><a:latin typeface="Poppins"/><a:ea typeface="Poppins"/><a:cs typeface="Poppins"/><a:sym typeface="Poppins"/></a:rPr><a:t>Even the all-powerful Pointing has no control about the blind texts.</a:t></a:r><a:endParaRPr b="1" i="0" sz="1200" u="none" cap="none" strike="noStrike"><a:solidFill><a:schemeClr val="dk1"/></a:solidFill><a:latin typeface="Poppins"/><a:ea typeface="Poppins"/><a:cs typeface="Poppins"/><a:sym typeface="Poppins"/></a:endParaRPr></a:p></p:txBody></p:sp><p:sp><p:nvSpPr><p:cNvPr id="482" name="Google Shape;482;p11"/><p:cNvSpPr txBox="1"/><p:nvPr/></p:nvSpPr><p:spPr><a:xfrm><a:off x="6745399" y="2935238"/><a:ext cx="4135306" cy="708143"/></a:xfrm><a:prstGeom prst="rect"><a:avLst/></a:prstGeom><a:noFill/><a:ln><a:noFill/></a:ln></p:spPr><p:txBody><a:bodyPr anchorCtr="0" anchor="t" bIns="45700" lIns="91425" spcFirstLastPara="1" rIns="91425" wrap="square" tIns="45700"><a:spAutoFit/></a:bodyPr><a:lstStyle/><a:p><a:pPr indent="0" lvl="0" marL="0" marR="0" rtl="0" algn="l"><a:lnSpc><a:spcPct val="150000"/></a:lnSpc><a:spcBef><a:spcPts val="0"/></a:spcBef><a:spcAft><a:spcPts val="0"/></a:spcAft><a:buClr><a:srgbClr val="000000"/></a:buClr><a:buSzPts val="1400"/><a:buFont typeface="Arial"/><a:buNone/></a:pPr><a:r><a:rPr b="0" i="0" lang="en-US" sz="1400" u="none" cap="none" strike="noStrike"><a:solidFill><a:schemeClr val="dk1"/></a:solidFill><a:latin typeface="Poppins"/><a:ea typeface="Poppins"/><a:cs typeface="Poppins"/><a:sym typeface="Poppins"/></a:rPr><a:t>Unlocking Success Through Our Distinctive Strengths That Set You Apart.</a:t></a:r><a:endParaRPr b="0" i="0" sz="1400" u="none" cap="none" strike="noStrike"><a:solidFill><a:srgbClr val="000000"/></a:solidFill><a:latin typeface="Arial"/><a:ea typeface="Arial"/><a:cs typeface="Arial"/><a:sym typeface="Arial"/></a:endParaRPr></a:p></p:txBody></p:sp><p:grpSp><p:nvGrpSpPr><p:cNvPr id="483" name="Google Shape;483;p11"/><p:cNvGrpSpPr/><p:nvPr/></p:nvGrpSpPr><p:grpSpPr><a:xfrm><a:off x="1062242" y="4481353"/><a:ext cx="448594" cy="448594"/><a:chOff x="969134" y="4249768"/><a:chExt cx="446149" cy="446149"/></a:xfrm></p:grpSpPr><p:sp><p:nvSpPr><p:cNvPr id="484" name="Google Shape;484;p11"/><p:cNvSpPr/><p:nvPr/></p:nvSpPr><p:spPr><a:xfrm><a:off x="969134" y="4249768"/><a:ext cx="446149" cy="446149"/></a:xfrm><a:prstGeom prst="ellipse"><a:avLst/></a:prstGeom><a:solidFill><a:schemeClr val="accent3"/></a:solidFill><a:ln><a:noFill/></a:ln></p:spPr><p:txBody><a:bodyPr anchorCtr="0" anchor="ctr" bIns="45700" lIns="91425" spcFirstLastPara="1" rIns="91425" wrap="square" tIns="45700"><a:noAutofit/></a:bodyPr><a:lstStyle/><a:p><a:pPr indent="0" lvl="0" marL="0" marR="0" rtl="0" algn="ctr"><a:lnSpc><a:spcPct val="100000"/></a:lnSpc><a:spcBef><a:spcPts val="0"/></a:spcBef><a:spcAft><a:spcPts val="0"/></a:spcAft><a:buClr><a:srgbClr val="000000"/></a:buClr><a:buSzPts val="1800"/><a:buFont typeface="Arial"/><a:buNone/></a:pPr><a:r><a:t></a:t></a:r><a:endParaRPr b="0" i="0" sz="1800" u="none" cap="none" strike="noStrike"><a:solidFill><a:schemeClr val="lt1"/></a:solidFill><a:latin typeface="Poppins"/><a:ea typeface="Poppins"/><a:cs typeface="Poppins"/><a:sym typeface="Poppins"/></a:endParaRPr></a:p></p:txBody></p:sp><p:sp><p:nvSpPr><p:cNvPr id="485" name="Google Shape;485;p11"/><p:cNvSpPr/><p:nvPr/></p:nvSpPr><p:spPr><a:xfrm><a:off x="1101086" y="4346251"/><a:ext cx="182243" cy="253182"/></a:xfrm><a:custGeom><a:rect b="b" l="l" r="r" t="t"/><a:pathLst><a:path extrusionOk="0" h="560125" w="403184"><a:moveTo><a:pt x="6479" y="294415"/></a:moveTo><a:lnTo><a:pt x="255368" y="6950"/></a:lnTo><a:cubicBezTo><a:pt x="263759" y="-2480"/><a:pt x="278209" y="-3318"/><a:pt x="287638" y="5083"/></a:cubicBezTo><a:cubicBezTo><a:pt x="293125" y="9960"/><a:pt x="295925" y="17170"/><a:pt x="295182" y="24476"/></a:cubicBezTo><a:lnTo><a:pt x="269179" y="182687"/></a:lnTo><a:cubicBezTo><a:pt x="268208" y="192592"/><a:pt x="273751" y="201993"/><a:pt x="282895" y="205928"/></a:cubicBezTo><a:lnTo><a:pt x="389956" y="252028"/></a:lnTo><a:cubicBezTo><a:pt x="401576" y="256972"/><a:pt x="406977" y="270402"/><a:pt x="402034" y="282013"/></a:cubicBezTo><a:cubicBezTo><a:pt x="401005" y="284442"/><a:pt x="399557" y="286671"/><a:pt x="397767" y="288604"/></a:cubicBezTo><a:lnTo><a:pt x="155260" y="552066"/></a:lnTo><a:cubicBezTo><a:pt x="146640" y="561362"/><a:pt x="132114" y="561915"/><a:pt x="122818" y="553304"/></a:cubicBezTo><a:cubicBezTo><a:pt x="117417" y="548294"/><a:pt x="114741" y="540998"/><a:pt x="115636" y="533683"/></a:cubicBezTo><a:lnTo><a:pt x="132876" y="396713"/></a:lnTo><a:cubicBezTo><a:pt x="134124" y="386379"/><a:pt x="128323" y="376472"/><a:pt x="118684" y="372520"/></a:cubicBezTo><a:lnTo><a:pt x="15433" y="330991"/></a:lnTo><a:cubicBezTo><a:pt x="3631" y="326504"/><a:pt x="-2303" y="313302"/><a:pt x="2174" y="301501"/></a:cubicBezTo><a:cubicBezTo><a:pt x="3164" y="298901"/><a:pt x="4622" y="296500"/><a:pt x="6479" y="294415"/></a:cubicBezTo><a:close/></a:path></a:pathLst></a:custGeom><a:solidFill><a:schemeClr val="lt2"/></a:solidFill><a:ln><a:noFill/></a:ln></p:spPr><p:txBody><a:bodyPr anchorCtr="0" anchor="ctr" bIns="45700" lIns="91425" spcFirstLastPara="1" rIns="91425" wrap="square" tIns="45700"><a:noAutofit/></a:bodyPr><a:lstStyle/><a:p><a:pPr indent="0" lvl="0" marL="0" marR="0" rtl="0" algn="l"><a:lnSpc><a:spcPct val="100000"/></a:lnSpc><a:spcBef><a:spcPts val="0"/></a:spcBef><a:spcAft><a:spcPts val="0"/></a:spcAft><a:buClr><a:srgbClr val="000000"/></a:buClr><a:buSzPts val="1800"/><a:buFont typeface="Arial"/><a:buNone/></a:pPr><a:r><a:t></a:t></a:r><a:endParaRPr b="0" i="0" sz="1800" u="none" cap="none" strike="noStrike"><a:solidFill><a:schemeClr val="dk1"/></a:solidFill><a:latin typeface="Poppins"/><a:ea typeface="Poppins"/><a:cs typeface="Poppins"/><a:sym typeface="Poppins"/></a:endParaRPr></a:p></p:txBody></p:sp></p:grpSp><p:grpSp><p:nvGrpSpPr><p:cNvPr id="486" name="Google Shape;486;p11"/><p:cNvGrpSpPr/><p:nvPr/></p:nvGrpSpPr><p:grpSpPr><a:xfrm flipH="1"><a:off x="4880387" y="4192111"/><a:ext cx="2081318" cy="1870536"/><a:chOff x="5857493" y="3214687"/><a:chExt cx="478726" cy="430244"/></a:xfrm></p:grpSpPr><p:sp><p:nvSpPr><p:cNvPr id="487" name="Google Shape;487;p11"/><p:cNvSpPr/><p:nvPr/></p:nvSpPr><p:spPr><a:xfrm><a:off x="5857874" y="3214687"/><a:ext cx="9525" cy="430244"/></a:xfrm><a:custGeom><a:rect b="b" l="l" r="r" t="t"/><a:pathLst><a:path extrusionOk="0" h="430244" w="9525"><a:moveTo><a:pt x="0" y="0"/></a:moveTo><a:lnTo><a:pt x="0" y="430244"/></a:lnTo></a:path></a:pathLst></a:custGeom><a:noFill/><a:ln cap="flat" cmpd="sng" w="19050"><a:solidFill><a:schemeClr val="accent3"/></a:solidFill><a:prstDash val="solid"/><a:miter lim="8000"/><a:headEnd len="sm" w="sm" type="none"/><a:tailEnd len="sm" w="sm" type="none"/></a:ln></p:spPr><p:txBody><a:bodyPr anchorCtr="0" anchor="ctr" bIns="45700" lIns="91425" spcFirstLastPara="1" rIns="91425" wrap="square" tIns="45700"><a:noAutofit/></a:bodyPr><a:lstStyle/><a:p><a:pPr indent="0" lvl="0" marL="0" marR="0" rtl="0" algn="l"><a:lnSpc><a:spcPct val="100000"/></a:lnSpc><a:spcBef><a:spcPts val="0"/></a:spcBef><a:spcAft><a:spcPts val="0"/></a:spcAft><a:buClr><a:srgbClr val="000000"/></a:buClr><a:buSzPts val="1800"/><a:buFont typeface="Arial"/><a:buNone/></a:pPr><a:r><a:t></a:t></a:r><a:endParaRPr b="0" i="0" sz="1800" u="none" cap="none" strike="noStrike"><a:solidFill><a:schemeClr val="dk1"/></a:solidFill><a:latin typeface="Poppins"/><a:ea typeface="Poppins"/><a:cs typeface="Poppins"/><a:sym typeface="Poppins"/></a:endParaRPr></a:p></p:txBody></p:sp><p:sp><p:nvSpPr><p:cNvPr id="488" name="Google Shape;488;p11"/><p:cNvSpPr/><p:nvPr/></p:nvSpPr><p:spPr><a:xfrm><a:off x="5857493" y="3402139"/><a:ext cx="478726" cy="55340"/></a:xfrm><a:custGeom><a:rect b="b" l="l" r="r" t="t"/><a:pathLst><a:path extrusionOk="0" h="55340" w="478726"><a:moveTo><a:pt x="597" y="-624"/></a:moveTo><a:cubicBezTo><a:pt x="8112" y="9197"/><a:pt x="18599" y="16312"/><a:pt x="30506" y="19665"/></a:cubicBezTo><a:cubicBezTo><a:pt x="40383" y="21579"/><a:pt x="50460" y="22313"/><a:pt x="60509" y="21855"/></a:cubicBezTo><a:lnTo><a:pt x="120326" y="22808"/></a:lnTo><a:lnTo><a:pt x="239960" y="23951"/></a:lnTo><a:lnTo><a:pt x="359309" y="23951"/></a:lnTo><a:cubicBezTo><a:pt x="399123" y="23951"/><a:pt x="439033" y="23380"/><a:pt x="478943" y="22236"/></a:cubicBezTo><a:lnTo><a:pt x="478943" y="31761"/></a:lnTo><a:cubicBezTo><a:pt x="439033" y="30713"/><a:pt x="399123" y="30523"/><a:pt x="359309" y="30047"/></a:cubicBezTo><a:lnTo><a:pt x="239579" y="30047"/></a:lnTo><a:lnTo><a:pt x="119945" y="31285"/></a:lnTo><a:lnTo><a:pt x="60128" y="32238"/></a:lnTo><a:cubicBezTo><a:pt x="50080" y="31733"/><a:pt x="40002" y="32466"/><a:pt x="30125" y="34428"/></a:cubicBezTo><a:cubicBezTo><a:pt x="18218" y="37781"/><a:pt x="7731" y="44896"/><a:pt x="216" y="54717"/></a:cubicBezTo><a:close/></a:path></a:pathLst></a:custGeom><a:solidFill><a:schemeClr val="accent3"/></a:solidFill><a:ln><a:noFill/></a:ln></p:spPr><p:txBody><a:bodyPr anchorCtr="0" anchor="ctr" bIns="45700" lIns="91425" spcFirstLastPara="1" rIns="91425" wrap="square" tIns="45700"><a:noAutofit/></a:bodyPr><a:lstStyle/><a:p><a:pPr indent="0" lvl="0" marL="0" marR="0" rtl="0" algn="l"><a:lnSpc><a:spcPct val="100000"/></a:lnSpc><a:spcBef><a:spcPts val="0"/></a:spcBef><a:spcAft><a:spcPts val="0"/></a:spcAft><a:buClr><a:srgbClr val="000000"/></a:buClr><a:buSzPts val="1800"/><a:buFont typeface="Arial"/><a:buNone/></a:pPr><a:r><a:t></a:t></a:r><a:endParaRPr b="0" i="0" sz="1800" u="none" cap="none" strike="noStrike"><a:solidFill><a:schemeClr val="dk1"/></a:solidFill><a:latin typeface="Poppins"/><a:ea typeface="Poppins"/><a:cs typeface="Poppins"/><a:sym typeface="Poppins"/></a:endParaRPr></a:p></p:txBody></p:sp></p:grpSp><p:grpSp><p:nvGrpSpPr><p:cNvPr id="489" name="Google Shape;489;p11"/><p:cNvGrpSpPr/><p:nvPr/></p:nvGrpSpPr><p:grpSpPr><a:xfrm><a:off x="1838517" y="4457343"/><a:ext cx="4465737" cy="1700892"/><a:chOff x="879098" y="3672466"/><a:chExt cx="5844773" cy="2334634"/></a:xfrm></p:grpSpPr><p:sp><p:nvSpPr><p:cNvPr id="490" name="Google Shape;490;p11"/><p:cNvSpPr/><p:nvPr/></p:nvSpPr><p:spPr><a:xfrm><a:off x="952500" y="3774444"/><a:ext cx="5771371" cy="2232656"/></a:xfrm><a:prstGeom prst="roundRect"><a:avLst><a:gd fmla="val 4987" name="adj"/></a:avLst></a:prstGeom><a:solidFill><a:schemeClr val="accent3"/></a:solidFill><a:ln><a:noFill/></a:ln></p:spPr><p:txBody><a:bodyPr anchorCtr="0" anchor="ctr" bIns="45700" lIns="91425" spcFirstLastPara="1" rIns="91425" wrap="square" tIns="45700"><a:noAutofit/></a:bodyPr><a:lstStyle/><a:p><a:pPr indent="0" lvl="0" marL="0" marR="0" rtl="0" algn="ctr"><a:lnSpc><a:spcPct val="100000"/></a:lnSpc><a:spcBef><a:spcPts val="0"/></a:spcBef><a:spcAft><a:spcPts val="0"/></a:spcAft><a:buClr><a:srgbClr val="000000"/></a:buClr><a:buSzPts val="1800"/><a:buFont typeface="Arial"/><a:buNone/></a:pPr><a:r><a:t></a:t></a:r><a:endParaRPr b="0" i="0" sz="1800" u="none" cap="none" strike="noStrike"><a:solidFill><a:schemeClr val="lt1"/></a:solidFill><a:latin typeface="Poppins"/><a:ea typeface="Poppins"/><a:cs typeface="Poppins"/><a:sym typeface="Poppins"/></a:endParaRPr></a:p></p:txBody></p:sp><p:sp><p:nvSpPr><p:cNvPr id="491" name="Google Shape;491;p11"/><p:cNvSpPr/><p:nvPr/></p:nvSpPr><p:spPr><a:xfrm><a:off x="879098" y="3672466"/><a:ext cx="5771371" cy="2232656"/></a:xfrm><a:prstGeom prst="roundRect"><a:avLst><a:gd fmla="val 4987" name="adj"/></a:avLst></a:prstGeom><a:solidFill><a:schemeClr val="accent2"/></a:solidFill><a:ln><a:noFill/></a:ln></p:spPr><p:txBody><a:bodyPr anchorCtr="0" anchor="ctr" bIns="45700" lIns="91425" spcFirstLastPara="1" rIns="91425" wrap="square" tIns="45700"><a:noAutofit/></a:bodyPr><a:lstStyle/><a:p><a:pPr indent="0" lvl="0" marL="0" marR="0" rtl="0" algn="ctr"><a:lnSpc><a:spcPct val="100000"/></a:lnSpc><a:spcBef><a:spcPts val="0"/></a:spcBef><a:spcAft><a:spcPts val="0"/></a:spcAft><a:buClr><a:srgbClr val="000000"/></a:buClr><a:buSzPts val="1800"/><a:buFont typeface="Arial"/><a:buNone/></a:pPr><a:r><a:t></a:t></a:r><a:endParaRPr b="0" i="0" sz="1800" u="none" cap="none" strike="noStrike"><a:solidFill><a:schemeClr val="lt1"/></a:solidFill><a:latin typeface="Poppins"/><a:ea typeface="Poppins"/><a:cs typeface="Poppins"/><a:sym typeface="Poppins"/></a:endParaRPr></a:p></p:txBody></p:sp></p:grpSp><p:sp><p:nvSpPr><p:cNvPr id="492" name="Google Shape;492;p11"/><p:cNvSpPr/><p:nvPr/></p:nvSpPr><p:spPr><a:xfrm><a:off x="2066192" y="4727269"/><a:ext cx="2560316" cy="400110"/></a:xfrm><a:prstGeom prst="rect"><a:avLst/></a:prstGeom><a:noFill/><a:ln><a:noFill/></a:ln></p:spPr><p:txBody><a:bodyPr anchorCtr="0" anchor="t" bIns="45700" lIns="91425" spcFirstLastPara="1" rIns="91425" wrap="square" tIns="45700"><a:spAutoFit/></a:bodyPr><a:lstStyle/><a:p><a:pPr indent="0" lvl="0" marL="0" marR="0" rtl="0" algn="l"><a:lnSpc><a:spcPct val="100000"/></a:lnSpc><a:spcBef><a:spcPts val="0"/></a:spcBef><a:spcAft><a:spcPts val="0"/></a:spcAft><a:buClr><a:srgbClr val="000000"/></a:buClr><a:buSzPts val="2000"/><a:buFont typeface="Arial"/><a:buNone/></a:pPr><a:r><a:rPr b="0" i="0" lang="en-US" sz="2000" u="none" cap="none" strike="noStrike"><a:solidFill><a:schemeClr val="lt1"/></a:solidFill><a:latin typeface="Poppins"/><a:ea typeface="Poppins"/><a:cs typeface="Poppins"/><a:sym typeface="Poppins"/></a:rPr><a:t>Enhanced Security</a:t></a:r><a:endParaRPr b="0" i="0" sz="1400" u="none" cap="none" strike="noStrike"><a:solidFill><a:srgbClr val="000000"/></a:solidFill><a:latin typeface="Arial"/><a:ea typeface="Arial"/><a:cs typeface="Arial"/><a:sym typeface="Arial"/></a:endParaRPr></a:p></p:txBody></p:sp><p:sp><p:nvSpPr><p:cNvPr id="493" name="Google Shape;493;p11"/><p:cNvSpPr/><p:nvPr/></p:nvSpPr><p:spPr><a:xfrm><a:off x="2066193" y="5200453"/><a:ext cx="3422310" cy="620170"/></a:xfrm><a:prstGeom prst="rect"><a:avLst/></a:prstGeom><a:noFill/><a:ln><a:noFill/></a:ln></p:spPr><p:txBody><a:bodyPr anchorCtr="0" anchor="t" bIns="45700" lIns="91425" spcFirstLastPara="1" rIns="91425" wrap="square" tIns="45700"><a:spAutoFit/></a:bodyPr><a:lstStyle/><a:p><a:pPr indent="0" lvl="0" marL="0" marR="0" rtl="0" algn="l"><a:lnSpc><a:spcPct val="150000"/></a:lnSpc><a:spcBef><a:spcPts val="0"/></a:spcBef><a:spcAft><a:spcPts val="0"/></a:spcAft><a:buClr><a:srgbClr val="000000"/></a:buClr><a:buSzPts val="1200"/><a:buFont typeface="Arial"/><a:buNone/></a:pPr><a:r><a:rPr b="0" i="0" lang="en-US" sz="1200" u="none" cap="none" strike="noStrike"><a:solidFill><a:schemeClr val="lt1"/></a:solidFill><a:latin typeface="Poppins"/><a:ea typeface="Poppins"/><a:cs typeface="Poppins"/><a:sym typeface="Poppins"/></a:rPr><a:t>When she reached the first hills of the Italic Mountains, she had a last view back.</a:t></a:r><a:endParaRPr b="0" i="0" sz="1400" u="none" cap="none" strike="noStrike"><a:solidFill><a:srgbClr val="000000"/></a:solidFill><a:latin typeface="Arial"/><a:ea typeface="Arial"/><a:cs typeface="Arial"/><a:sym typeface="Arial"/></a:endParaRPr></a:p></p:txBody></p:sp><p:pic><p:nvPicPr><p:cNvPr id="494" name="Google Shape;494;p11"/><p:cNvPicPr preferRelativeResize="0"/><p:nvPr/></p:nvPicPr><p:blipFill rotWithShape="1"><a:blip r:embed="rId3"><a:alphaModFix/></a:blip><a:srcRect b="25670" l="7526" r="8517" t="25786"/><a:stretch/></p:blipFill><p:spPr><a:xfrm><a:off x="7361290" y="3969795"/><a:ext cx="3792780" cy="2192954"/></a:xfrm><a:custGeom><a:rect b="b" l="l" r="r" t="t"/><a:pathLst><a:path extrusionOk="0" h="2192954" w="3792780"><a:moveTo><a:pt x="23606" y="0"/></a:moveTo><a:lnTo><a:pt x="3769581" y="0"/></a:lnTo><a:cubicBezTo><a:pt x="3782452" y="220"/><a:pt x="3792780" y="10724"/><a:pt x="3792780" y="23604"/></a:cubicBezTo><a:lnTo><a:pt x="3792780" y="1401514"/></a:lnTo><a:cubicBezTo><a:pt x="3792903" y="1838424"/><a:pt x="3438861" y="2192732"/><a:pt x="3001945" y="2192954"/></a:cubicBezTo><a:lnTo><a:pt x="23606" y="2192954"/></a:lnTo><a:cubicBezTo><a:pt x="10569" y="2192954"/><a:pt x="0" y="2182381"/><a:pt x="0" y="2169349"/></a:cubicBezTo><a:cubicBezTo><a:pt x="0" y="2169289"/><a:pt x="0" y="2169209"/><a:pt x="0" y="2169147"/></a:cubicBezTo><a:lnTo><a:pt x="0" y="23604"/></a:lnTo><a:cubicBezTo><a:pt x="0" y="10567"/><a:pt x="10569" y="0"/><a:pt x="23606" y="0"/></a:cubicBezTo><a:close/></a:path></a:pathLst></a:custGeom><a:noFill/><a:ln><a:noFill/></a:ln></p:spPr></p:pic></p:spTree></p:cSld><p:clrMapOvr><a:masterClrMapping/></p:clrMapOvr></p:sld>